[
  {
    "full_name": "endrissuofe/node-cicd-yaml-project",
    "stargazers_count": 1,
    "open_issues_count": 0,
    "forks_count": 0
  },
  {
    "full_name": "MIATECHPARTNERS/PromptChains",
    "stargazers_count": 1130,
    "open_issues_count": 0,
    "forks_count": 140
  },
  {
    "full_name": "thetechfusionist/Infographics",
    "stargazers_count": 108,
    "open_issues_count": 0,
    "forks_count": 19
  },
  {
    "full_name": "ViktorUJ/cks",
    "stargazers_count": 1342,
    "open_issues_count": 2,
    "forks_count": 258
  }
]